nanotopy/__init__.py
nanotopy/client.py
nanotopy/src/__init__.py
nanotopy/src/nano_local.py
nanotopy-0.1.0.dist-info/METADATA
nanotopy-0.1.0.dist-info/WHEEL
nanotopy-0.1.0.dist-info/top_level.txt
nanotopy-0.1.0.dist-info/RECORD
