Metadata-Version: 2.1
Name: nanotopy
Version: 0.1.0
Summary: async extended nano.to library for ease of use
Home-page: https://github.com/gr0vity-dev/nanotopy
Author: gr0vity
Classifier: Development Status :: 4 - Beta
Classifier: Intended Audience :: Developers
Classifier: License :: OSI Approved :: MIT License
Classifier: Programming Language :: Python :: 3
Classifier: Programming Language :: Python :: 3.7
Classifier: Programming Language :: Python :: 3.8
Classifier: Programming Language :: Python :: 3.9
Classifier: Programming Language :: Python :: 3.10
Requires-Python: >=3.7
Requires-Dist: nanorpc
Requires-Dist: asyncio
